{
  "/etc/issue.net": "Ubuntu 24.04.4 LTS",
  "antiFeatures": {},
  "apksigner": "/home/runner/work/_temp/revancedbot-cache/shims/apksigner",
  "archivePolicy0": [],
  "commandLine": [
    "/home/runner/.local/share/mise/installs/pipx-fdroidserver/2.4.5/bin/fdroid update",
    "--pretty",
    "--delete-unknown",
    "-c"
  ],
  "disabled": [],
  "endTimestamp": 1784503021089,
  "failedBuilds": {},
  "jarsigner": "/home/runner/.local/share/mise/installs/java/temurin-21.0.7+6.0.LTS/bin/jarsigner",
  "keytool": "/home/runner/.local/share/mise/installs/java/temurin-21.0.7+6.0.LTS/bin/keytool",
  "needsUpdate": [
    "at.gv.oe.app.revanced",
    "at.willhaben.revanced",
    "ch.protonvpn.android.revanced",
    "com.andrewshu.android.reddit.revanced",
    "com.bandcamp.android.revanced",
    "com.nis.app.revanced",
    "com.onelouder.baconreader.revanced",
    "com.pandora.android.revanced",
    "com.rubenmayayo.reddit.revanced",
    "com.samsung.android.themedesigner.revanced",
    "com.sec.android.app.fm.revanced",
    "de.simon.openinghours.revanced",
    "eu.faircode.netguard.revanced",
    "ml.docilealligator.infinityforreddit.plus.revanced",
    "ml.docilealligator.infinityforreddit.revanced"
  ],
  "noPackages": [
    "at.gv.oe.app.revanced",
    "at.willhaben.revanced",
    "ch.protonvpn.android.revanced",
    "com.andrewshu.android.reddit.revanced",
    "com.bandcamp.android.revanced",
    "com.nis.app.revanced",
    "com.onelouder.baconreader.revanced",
    "com.pandora.android.revanced",
    "com.rubenmayayo.reddit.revanced",
    "com.samsung.android.themedesigner.revanced",
    "com.sec.android.app.fm.revanced",
    "de.simon.openinghours.revanced",
    "eu.faircode.netguard.revanced",
    "ml.docilealligator.infinityforreddit.plus.revanced",
    "ml.docilealligator.infinityforreddit.revanced"
  ],
  "noUpdateCheck": [
    "at.gv.oe.app.revanced",
    "at.willhaben.revanced",
    "ch.protonvpn.android.revanced",
    "com.andrewshu.android.reddit.revanced",
    "com.bandcamp.android.revanced",
    "com.nis.app.revanced",
    "com.onelouder.baconreader.revanced",
    "com.pandora.android.revanced",
    "com.rubenmayayo.reddit.revanced",
    "com.samsung.android.themedesigner.revanced",
    "com.sec.android.app.fm.revanced",
    "de.simon.openinghours.revanced",
    "eu.faircode.netguard.revanced",
    "ml.docilealligator.infinityforreddit.plus.revanced",
    "ml.docilealligator.infinityforreddit.revanced"
  ],
  "stages": {
    "delete_disabled_builds": 1784503004441,
    "index.make repo": 1784503018807,
    "prepare_apps repo": 1784503018805,
    "process_apks": 1784503004441,
    "read_added_date_from_all_apks": 1784503018805,
    "remove_apks": 1784503018803,
    "scan_repo_files": 1784503018803
  },
  "startTimestamp": 1784503004000,
  "subcommand": "update"
}